thermopt/__init__.py
thermopt/components/__init__.py
thermopt/components/basic_components.py
thermopt/components/heat_exchanger_plates.py
thermopt/components/turbomachinery_nondimensional.py
thermopt/config.py
thermopt/cycles/__init__.py
thermopt/cycles/cycle_PTES_recuperated.py
thermopt/cycles/cycle_PTES_recuperated_turbo.py
thermopt/cycles/cycle_power_recuperated.py
thermopt/cycles/cycle_power_simple.py
thermopt/cycles/cycle_power_split_compression.py
thermopt/cycles/cycle_refrigeration_recuperated.py
thermopt/cycles/cycle_refrigeration_simple.py
thermopt/math.py
thermopt/optimize_cycle.py
thermopt/utilities/__init__.py
thermopt/utilities/file_utils.py
thermopt/utilities/graphics.py
thermopt/utilities/numerics.py
thermopt/utilities/optimization_utils.py
thermopt-0.2.2.dist-info/LICENSE.md
thermopt-0.2.2.dist-info/METADATA
thermopt-0.2.2.dist-info/WHEEL
thermopt-0.2.2.dist-info/RECORD
