Metadata-Version: 2.1
Name: thermopt
Version: 0.2.2
Summary: A Python tool for the analysis and optimization of thermodynamic cycles.
Home-page: https://github.com/turbo-sim/thermopt
License: MIT
Author: Roberto Agromayor
Requires-Python: >=3.10,<3.14
Classifier: License :: OSI Approved :: MIT License
Classifier: Programming Language :: Python :: 3
Classifier: Programming Language :: Python :: 3.10
Classifier: Programming Language :: Python :: 3.11
Classifier: Programming Language :: Python :: 3.12
Requires-Dist: PyYAML (>=6.0.2,<7.0.0)
Requires-Dist: coolpropx (>=0.2.8,<0.3.0)
Requires-Dist: cycler (>=0.12.1,<0.13.0)
Requires-Dist: imageio[ffmpeg] (>=2.37.0,<3.0.0)
Requires-Dist: matplotlib (>=3.10.1,<4.0.0)
Requires-Dist: numpy (>=2.2.4,<3.0.0)
Requires-Dist: openpyxl (>=3.1.5,<4.0.0)
Requires-Dist: pandas (>=2.2.3,<3.0.0)
Requires-Dist: pysolver_view (>=0.6.2,<0.7.0)
Requires-Dist: scipy (>=1.15.2,<2.0.0)
Requires-Dist: spyder-kernels (==3.0.2)
Requires-Dist: toml (>=0.10.2,<0.11.0)
Project-URL: Documentation, https://github.com/turbo-sim/thermopt
Project-URL: Repository, https://github.com/turbo-sim/thermopt
